LICENSE
MANIFEST.in
README.md
requirements-dev.txt
setup.cfg
setup.py
techcombine/__init__.py
techcombine/tests/__init__.py
techcombine/tests/utils/__init__.py
techcombine/tests/utils/line_notify.py
techcombine/tests/utils/test_error_response.py
techcombine/tests/utils/test_file_utils.py
techcombine/utils/__init__.py
techcombine/utils/error_response.py
techcombine/utils/file_utils.py
techcombine/utils/line_notify.py
techcombine/utils/slug.py
test2techcombine.egg-info/PKG-INFO
test2techcombine.egg-info/SOURCES.txt
test2techcombine.egg-info/dependency_links.txt
test2techcombine.egg-info/requires.txt
test2techcombine.egg-info/top_level.txt